{"2010": {"density": "25.00025", "totalPop": "6525", "mAge": "43.8", "mIncome": "35199"}, "2016": {"density": "24.21863", "totalPop": "6321", "mAge": "48.6", "mIncome": "35776"}, "2017": {"density": "24.48585", "totalPop": "6392", "mAge": "47.2", "mIncome": "32482"}, "2011": {"density": "24.51748", "totalPop": "6399", "mAge": "43.4", "mIncome": "33390"}, "2018": {"density": "23.58499", "totalPop": "6157", "mAge": "46.1", "mIncome": "37357"}, "2012": {"density": "23.95043", "totalPop": "6251", "mAge": "45.2", "mIncome": "34500"}, "2014": {"density": "24.91978", "totalPop": "6504", "mAge": "47.2", "mIncome": "32109"}, "2015": {"density": "24.80101", "totalPop": "6473", "mAge": "47.2", "mIncome": "33719"}, "2013": {"density": "25.09603", "totalPop": "6550", "mAge": "45.4", "mIncome": "32250"}, "2019": {"density": "22.77673", "totalPop": "5946", "mAge": "45", "mIncome": "39360"}, "name": "Census Tract 9540, Chambers County, Alabama"}