{"2010": {"density": "2984.72", "totalPop": "12263", "mAge": "23.9", "mIncome": "39432"}, "2016": {"density": "3541.576", "totalPop": "14561", "mAge": "24.8", "mIncome": "41751"}, "2017": {"density": "3594.112", "totalPop": "14777", "mAge": "25.2", "mIncome": "46409"}, "2011": {"density": "3010.273", "totalPop": "12368", "mAge": "24.8", "mIncome": "38696"}, "2018": {"density": "3776.54", "totalPop": "15534", "mAge": "25.7", "mIncome": "50119"}, "2012": {"density": "3262.305", "totalPop": "13412", "mAge": "25", "mIncome": "39244"}, "2014": {"density": "3631.302", "totalPop": "14928", "mAge": "24", "mIncome": "41946"}, "2015": {"density": "3605.301", "totalPop": "14823", "mAge": "24.8", "mIncome": "41514"}, "2013": {"density": "3225.067", "totalPop": "13258", "mAge": "24.5", "mIncome": "39351"}, "2019": {"density": "3753.446", "totalPop": "15439", "mAge": "26", "mIncome": "44233"}, "name": "Census Tract 103.02, Washington County, Arkansas"}