{"2010": {"density": "4286.752", "totalPop": "4743", "mAge": "44.4", "mIncome": "105082"}, "2016": {"density": "4256.928", "totalPop": "4710", "mAge": "44.3", "mIncome": "95587"}, "2017": {"density": "4160.22", "totalPop": "4603", "mAge": "46.7", "mIncome": "98576"}, "2011": {"density": "4472.938", "totalPop": "4949", "mAge": "44.4", "mIncome": "104489"}, "2018": {"density": "4148.454", "totalPop": "4590", "mAge": "46.9", "mIncome": "105192"}, "2012": {"density": "4521.745", "totalPop": "5003", "mAge": "45.2", "mIncome": "90846"}, "2020": {"density": "3711.013", "totalPop": "4106", "mAge": "47.3", "mIncome": "151406"}, "2014": {"density": "4514.513", "totalPop": "4995", "mAge": "45", "mIncome": "89659"}, "2015": {"density": "4430.458", "totalPop": "4902", "mAge": "45.1", "mIncome": "81867"}, "2022": {"density": "3834.834", "totalPop": "4243", "mAge": "45.6", "mIncome": "175673"}, "2013": {"density": "4576.875", "totalPop": "5064", "mAge": "43.9", "mIncome": "92567"}, "2021": {"density": "3952.328", "totalPop": "4373", "mAge": "45.9", "mIncome": "156076"}, "2019": {"density": "4017.402", "totalPop": "4445", "mAge": "46.3", "mIncome": "126328"}, "name": "Census Tract 1393.01, Los Angeles County, California"}