{"2010": {"density": "39602.31", "totalPop": "4961", "mAge": "26.5", "mIncome": "28429"}, "2016": {"density": "38364.99", "totalPop": "4806", "mAge": "28.3", "mIncome": "36442"}, "2017": {"density": "40719.89", "totalPop": "5101", "mAge": "27.7", "mIncome": "37479"}, "2011": {"density": "38572.54", "totalPop": "4832", "mAge": "26.6", "mIncome": "26827"}, "2018": {"density": "41302.63", "totalPop": "5174", "mAge": "28.4", "mIncome": "40982"}, "2012": {"density": "38333.06", "totalPop": "4802", "mAge": "25.8", "mIncome": "30268"}, "2020": {"density": "38357.01", "totalPop": "4805", "mAge": "27.8", "mIncome": "46056"}, "2014": {"density": "38189.37", "totalPop": "4784", "mAge": "27.5", "mIncome": "32703"}, "2015": {"density": "38971.68", "totalPop": "4882", "mAge": "27.9", "mIncome": "38468"}, "2022": {"density": "34102.21", "totalPop": "4272", "mAge": "31.2", "mIncome": "54478"}, "2013": {"density": "35315.59", "totalPop": "4424", "mAge": "27.2", "mIncome": "30398"}, "2021": {"density": "37997.79", "totalPop": "4760", "mAge": "27.9", "mIncome": "49828"}, "2019": {"density": "40033.38", "totalPop": "5015", "mAge": "28.1", "mIncome": "45400"}, "name": "Census Tract 5764.02, Los Angeles County, California"}