{"2010": {"density": "2389.587", "totalPop": "5048", "mAge": "37.2", "mIncome": "38333"}, "2016": {"density": "2082.628", "totalPop": "4399", "mAge": "44.9", "mIncome": "44847"}, "2017": {"density": "2167.846", "totalPop": "4579", "mAge": "42.4", "mIncome": "47193"}, "2011": {"density": "2231.95", "totalPop": "4715", "mAge": "36.1", "mIncome": "38219"}, "2018": {"density": "2064.166", "totalPop": "4360", "mAge": "43.8", "mIncome": "49735"}, "2012": {"density": "2114.08", "totalPop": "4466", "mAge": "38.6", "mIncome": "39838"}, "2020": {"density": "2165.475", "totalPop": "4439", "mAge": "44.8", "mIncome": "47615"}, "2014": {"density": "2065.586", "totalPop": "4363", "mAge": "46.2", "mIncome": "42324"}, "2015": {"density": "2167.373", "totalPop": "4578", "mAge": "44.9", "mIncome": "46448"}, "2022": {"density": "2166.938", "totalPop": "4442", "mAge": "46.5", "mIncome": "49358"}, "2013": {"density": "2100.617", "totalPop": "4437", "mAge": "41.8", "mIncome": "44336"}, "2021": {"density": "2137.669", "totalPop": "4382", "mAge": "46.9", "mIncome": "52069"}, "2019": {"density": "2161.693", "totalPop": "4566", "mAge": "42.8", "mIncome": "52583"}, "name": "Census Tract 203, Placer County, California"}