{"2010": {"density": "7.782352", "totalPop": "956", "mAge": "37.9", "mIncome": "67909"}, "2016": {"density": "9.719708", "totalPop": "1194", "mAge": "50.6", "mIncome": "56641"}, "2017": {"density": "8.962646", "totalPop": "1101", "mAge": "47.2", "mIncome": "70268"}, "2011": {"density": "8.474298", "totalPop": "1041", "mAge": "47.2", "mIncome": "67522"}, "2018": {"density": "9.418514", "totalPop": "1157", "mAge": "46.5", "mIncome": "75333"}, "2012": {"density": "9.40232", "totalPop": "1155", "mAge": "46.8", "mIncome": "46932"}, "2020": {"density": "11.14429", "totalPop": "1369", "mAge": "39.4", "mIncome": "91071"}, "2014": {"density": "9.345247", "totalPop": "1148", "mAge": "51.2", "mIncome": "50446"}, "2015": {"density": "9.605742", "totalPop": "1180", "mAge": "52.9", "mIncome": "52500"}, "2022": {"density": "13.4399", "totalPop": "1651", "mAge": "41.5", "mIncome": "114554"}, "2013": {"density": "9.239419", "totalPop": "1135", "mAge": "49.8", "mIncome": "50917"}, "2021": {"density": "11.83623", "totalPop": "1454", "mAge": "40.5", "mIncome": "91932"}, "2019": {"density": "10.72913", "totalPop": "1318", "mAge": "43.9", "mIncome": "76971"}, "name": "Census Tract 220.14, Placer County, California"}