{"2010": {"density": "28692.75", "totalPop": "3684", "mAge": "38", "mIncome": "72819"}, "2016": {"density": "24101.33", "totalPop": "3090", "mAge": "39.7", "mIncome": "104943"}, "2017": {"density": "24623.91", "totalPop": "3157", "mAge": "40", "mIncome": "113258"}, "2011": {"density": "28365.63", "totalPop": "3642", "mAge": "36.9", "mIncome": "63203"}, "2018": {"density": "23570.94", "totalPop": "3022", "mAge": "40.6", "mIncome": "128375"}, "2012": {"density": "28279.96", "totalPop": "3631", "mAge": "37.1", "mIncome": "65750"}, "2020": {"density": "22260.71", "totalPop": "2854", "mAge": "39.2", "mIncome": "148816"}, "2014": {"density": "27197.84", "totalPop": "3487", "mAge": "35.8", "mIncome": "81341"}, "2015": {"density": "26324.27", "totalPop": "3375", "mAge": "37.4", "mIncome": "82013"}, "2022": {"density": "22167.12", "totalPop": "2842", "mAge": "40.3", "mIncome": "155750"}, "2013": {"density": "27259.67", "totalPop": "3500", "mAge": "38.1", "mIncome": "66779"}, "2021": {"density": "20396.55", "totalPop": "2615", "mAge": "41.7", "mIncome": "147708"}, "2019": {"density": "22315.18", "totalPop": "2861", "mAge": "42.2", "mIncome": "130742"}, "name": "Census Tract 426.02, San Francisco County, California"}