{"2010": {"density": "935.1387", "totalPop": "2104", "mAge": "50", "mIncome": "87208"}, "2016": {"density": "1180.479", "totalPop": "2656", "mAge": "48.6", "mIncome": "90711"}, "2017": {"density": "1225.37", "totalPop": "2757", "mAge": "46.6", "mIncome": "79851"}, "2011": {"density": "1051.587", "totalPop": "2366", "mAge": "50.3", "mIncome": "89327"}, "2018": {"density": "1321.445", "totalPop": "2971", "mAge": "46.9", "mIncome": "89542"}, "2012": {"density": "1205.814", "totalPop": "2713", "mAge": "52.3", "mIncome": "86527"}, "2020": {"density": "1691.507", "totalPop": "3803", "mAge": "52.5", "mIncome": "94111"}, "2014": {"density": "1205.369", "totalPop": "2712", "mAge": "55.8", "mIncome": "87600"}, "2015": {"density": "1098.255", "totalPop": "2471", "mAge": "52", "mIncome": "84844"}, "2022": {"density": "1620.342", "totalPop": "3643", "mAge": "59.5", "mIncome": "112813"}, "2013": {"density": "1092.032", "totalPop": "2457", "mAge": "57.2", "mIncome": "88644"}, "2021": {"density": "1758.225", "totalPop": "3953", "mAge": "57.5", "mIncome": "105793"}, "2019": {"density": "1417.075", "totalPop": "3186", "mAge": "48.4", "mIncome": "91289"}, "name": "Census Tract 26.08, Bay County, Florida"}