{"2010": {"density": "4761.859", "totalPop": "4678", "mAge": "35.8", "mIncome": "30137"}, "2016": {"density": "4169.427", "totalPop": "4096", "mAge": "39.8", "mIncome": "34265"}, "2017": {"density": "4417.661", "totalPop": "4234", "mAge": "42.4", "mIncome": "38071"}, "2011": {"density": "4557.254", "totalPop": "4477", "mAge": "32.4", "mIncome": "34706"}, "2018": {"density": "4488.609", "totalPop": "4302", "mAge": "40.8", "mIncome": "38958"}, "2012": {"density": "4504.322", "totalPop": "4425", "mAge": "37.1", "mIncome": "29233"}, "2020": {"density": "4835.039", "totalPop": "4633", "mAge": "38", "mIncome": "38472"}, "2014": {"density": "4454.447", "totalPop": "4376", "mAge": "32.1", "mIncome": "33516"}, "2015": {"density": "4118.531", "totalPop": "4046", "mAge": "39.5", "mIncome": "33564"}, "2022": {"density": "4508.389", "totalPop": "4320", "mAge": "37.6", "mIncome": "44050"}, "2013": {"density": "4242.718", "totalPop": "4168", "mAge": "36.3", "mIncome": "32344"}, "2021": {"density": "4833.995", "totalPop": "4632", "mAge": "37.5", "mIncome": "41389"}, "2019": {"density": "4526.169", "totalPop": "4338", "mAge": "41.1", "mIncome": "42425"}, "name": "Census Tract 61, Palm Beach County, Florida"}