{"2010": {"density": "80.64439", "totalPop": "6123", "mAge": "40.3", "mIncome": "46852"}, "2016": {"density": "93.52533", "totalPop": "7101", "mAge": "40.3", "mIncome": "45792"}, "2017": {"density": "92.0872", "totalPop": "6992", "mAge": "39.9", "mIncome": "47823"}, "2011": {"density": "82.60683", "totalPop": "6272", "mAge": "41.5", "mIncome": "50307"}, "2018": {"density": "89.74084", "totalPop": "6814", "mAge": "42.6", "mIncome": "52848"}, "2012": {"density": "84.88537", "totalPop": "6445", "mAge": "41.2", "mIncome": "50537"}, "2020": {"density": "88.70041", "totalPop": "6735", "mAge": "47.4", "mIncome": "63441"}, "2014": {"density": "91.26001", "totalPop": "6929", "mAge": "41.3", "mIncome": "49180"}, "2015": {"density": "94.26289", "totalPop": "7157", "mAge": "41", "mIncome": "48698"}, "2022": {"density": "92.32217", "totalPop": "7010", "mAge": "41.6", "mIncome": "77386"}, "2013": {"density": "91.69464", "totalPop": "6962", "mAge": "40.9", "mIncome": "50252"}, "2021": {"density": "86.19809", "totalPop": "6545", "mAge": "44.8", "mIncome": "67108"}, "2019": {"density": "90.82078", "totalPop": "6896", "mAge": "44.3", "mIncome": "56344"}, "name": "Census Tract 9701, Lamar County, Georgia"}