{"2010": {"density": "14.56504", "totalPop": "1762", "mAge": "40.8", "mIncome": "30700"}, "2016": {"density": "13.39124", "totalPop": "1620", "mAge": "43.9", "mIncome": "40405"}, "2017": {"density": "14.81969", "totalPop": "1793", "mAge": "43", "mIncome": "41983"}, "2011": {"density": "16.63159", "totalPop": "2012", "mAge": "39.3", "mIncome": "31324"}, "2018": {"density": "14.75356", "totalPop": "1785", "mAge": "43.2", "mIncome": "43857"}, "2012": {"density": "17.03663", "totalPop": "2061", "mAge": "40.1", "mIncome": "33955"}, "2020": {"density": "13.48071", "totalPop": "1631", "mAge": "41.5", "mIncome": "47167"}, "2014": {"density": "16.16868", "totalPop": "1956", "mAge": "44.1", "mIncome": "30714"}, "2015": {"density": "14.40798", "totalPop": "1743", "mAge": "44.8", "mIncome": "34600"}, "2022": {"density": "16.52234", "totalPop": "1999", "mAge": "40.6", "mIncome": "72097"}, "2013": {"density": "18.29309", "totalPop": "2213", "mAge": "40.8", "mIncome": "33103"}, "2021": {"density": "14.01795", "totalPop": "1696", "mAge": "42.3", "mIncome": "48920"}, "2019": {"density": "14.48081", "totalPop": "1752", "mAge": "42.5", "mIncome": "43500"}, "name": "Census Tract 9601, Oglethorpe County, Georgia"}