{"2010": {"density": "2155.368", "totalPop": "4506", "mAge": "35.5", "mIncome": "31228"}, "2016": {"density": "2351.002", "totalPop": "4919", "mAge": "37.1", "mIncome": "33245"}, "2017": {"density": "2265.676", "totalPop": "4740", "mAge": "39.1", "mIncome": "36144"}, "2011": {"density": "2416.057", "totalPop": "5051", "mAge": "36.3", "mIncome": "34788"}, "2018": {"density": "2222.656", "totalPop": "4650", "mAge": "39.4", "mIncome": "36048"}, "2012": {"density": "2513.5", "totalPop": "5259", "mAge": "33.6", "mIncome": "32425"}, "2020": {"density": "2590.709", "totalPop": "5420", "mAge": "39.1", "mIncome": "29874"}, "2014": {"density": "2502.986", "totalPop": "5237", "mAge": "33.4", "mIncome": "31678"}, "2015": {"density": "2362.95", "totalPop": "4944", "mAge": "37.1", "mIncome": "34922"}, "2022": {"density": "2733.628", "totalPop": "5719", "mAge": "35", "mIncome": "34545"}, "2013": {"density": "2574.199", "totalPop": "5386", "mAge": "33.7", "mIncome": "32411"}, "2021": {"density": "2690.131", "totalPop": "5628", "mAge": "37.4", "mIncome": "35100"}, "2019": {"density": "2156.694", "totalPop": "4512", "mAge": "39.4", "mIncome": "38263"}, "name": "Census Tract 105.10, Richmond County, Georgia"}