{"2010": {"density": "79.25977", "totalPop": "6309", "mAge": "41.6", "mIncome": "57009"}, "2016": {"density": "74.37352", "totalPop": "5921", "mAge": "40.8", "mIncome": "58796"}, "2017": {"density": "76.52145", "totalPop": "6092", "mAge": "42.5", "mIncome": "60144"}, "2011": {"density": "76.63411", "totalPop": "6100", "mAge": "42.4", "mIncome": "58912"}, "2018": {"density": "75.547", "totalPop": "6015", "mAge": "44.3", "mIncome": "81000"}, "2012": {"density": "76.00645", "totalPop": "6051", "mAge": "41.9", "mIncome": "58880"}, "2020": {"density": "74.49397", "totalPop": "5932", "mAge": "47.9", "mIncome": "73710"}, "2014": {"density": "75.52913", "totalPop": "6013", "mAge": "44", "mIncome": "49792"}, "2015": {"density": "74.76291", "totalPop": "5952", "mAge": "42.1", "mIncome": "55398"}, "2022": {"density": "71.29169", "totalPop": "5677", "mAge": "47.6", "mIncome": "79040"}, "2013": {"density": "76.04413", "totalPop": "6054", "mAge": "43.1", "mIncome": "51156"}, "2021": {"density": "72.19586", "totalPop": "5749", "mAge": "50.1", "mIncome": "78154"}, "2019": {"density": "74.0042", "totalPop": "5893", "mAge": "43.5", "mIncome": "75057"}, "name": "Census Tract 106, Adams County, Illinois"}