{"2010": {"density": "1379.487", "totalPop": "2726", "mAge": "38.6", "mIncome": "44132"}, "2016": {"density": "1446.526", "totalPop": "2845", "mAge": "40.4", "mIncome": "71058"}, "2017": {"density": "1454.661", "totalPop": "2861", "mAge": "39.8", "mIncome": "52841"}, "2011": {"density": "1396.186", "totalPop": "2759", "mAge": "38.2", "mIncome": "51544"}, "2018": {"density": "1386.021", "totalPop": "2726", "mAge": "40.4", "mIncome": "53125"}, "2012": {"density": "1351.654", "totalPop": "2671", "mAge": "38.6", "mIncome": "53568"}, "2020": {"density": "1317.381", "totalPop": "2591", "mAge": "42", "mIncome": "55625"}, "2014": {"density": "1305.098", "totalPop": "2579", "mAge": "39.9", "mIncome": "61316"}, "2015": {"density": "1409.409", "totalPop": "2772", "mAge": "37.4", "mIncome": "66583"}, "2022": {"density": "1435.849", "totalPop": "2824", "mAge": "37.8", "mIncome": "70197"}, "2013": {"density": "1364.305", "totalPop": "2696", "mAge": "38.8", "mIncome": "54571"}, "2021": {"density": "1397.716", "totalPop": "2749", "mAge": "41.4", "mIncome": "62905"}, "2019": {"density": "1334.16", "totalPop": "2624", "mAge": "41.4", "mIncome": "48224"}, "name": "Census Tract 5502, Cook County, Illinois"}