{"2010": {"density": "1811.276", "totalPop": "5155", "mAge": "39.9", "mIncome": "84034"}, "2016": {"density": "1585.938", "totalPop": "4517", "mAge": "47.4", "mIncome": "79682"}, "2017": {"density": "1594.716", "totalPop": "4542", "mAge": "47", "mIncome": "84167"}, "2011": {"density": "1767.005", "totalPop": "5029", "mAge": "40.8", "mIncome": "81775"}, "2018": {"density": "1592.473", "totalPop": "4546", "mAge": "46.4", "mIncome": "84716"}, "2012": {"density": "1778.007", "totalPop": "5064", "mAge": "44.5", "mIncome": "86233"}, "2020": {"density": "1578.452", "totalPop": "4513", "mAge": "38.8", "mIncome": "101250"}, "2014": {"density": "1611.217", "totalPop": "4589", "mAge": "45.3", "mIncome": "87007"}, "2015": {"density": "1638.955", "totalPop": "4668", "mAge": "46.5", "mIncome": "77301"}, "2022": {"density": "1523.19", "totalPop": "4355", "mAge": "42.7", "mIncome": "109526"}, "2013": {"density": "1699.345", "totalPop": "4840", "mAge": "44.7", "mIncome": "85332"}, "2021": {"density": "1626.369", "totalPop": "4650", "mAge": "39.8", "mIncome": "108438"}, "2019": {"density": "1678.297", "totalPop": "4791", "mAge": "43.5", "mIncome": "91473"}, "name": "Census Tract 8444.02, DuPage County, Illinois"}