{"2010": {"density": "1270.621", "totalPop": "4886", "mAge": "30", "mIncome": "43856"}, "2016": {"density": "1093.522", "totalPop": "4205", "mAge": "35.5", "mIncome": "51786"}, "2017": {"density": "1012.17", "totalPop": "3890", "mAge": "35.8", "mIncome": "56169"}, "2011": {"density": "1212.369", "totalPop": "4662", "mAge": "33", "mIncome": "44754"}, "2018": {"density": "1077.184", "totalPop": "4131", "mAge": "35.3", "mIncome": "59333"}, "2012": {"density": "1201.707", "totalPop": "4621", "mAge": "35.1", "mIncome": "48717"}, "2020": {"density": "916.9037", "totalPop": "3537", "mAge": "36.5", "mIncome": "56796"}, "2014": {"density": "1121.87", "totalPop": "4314", "mAge": "36", "mIncome": "47522"}, "2015": {"density": "1104.184", "totalPop": "4246", "mAge": "37", "mIncome": "44842"}, "2022": {"density": "937.1238", "totalPop": "3615", "mAge": "34.8", "mIncome": "64565"}, "2013": {"density": "1184.023", "totalPop": "4553", "mAge": "35.3", "mIncome": "46492"}, "2021": {"density": "931.4207", "totalPop": "3593", "mAge": "37.3", "mIncome": "60000"}, "2019": {"density": "1045.893", "totalPop": "4011", "mAge": "35.4", "mIncome": "59663"}, "name": "Census Tract 108.13, Allen County, Indiana"}