{"2010": {"density": "2167.275", "totalPop": "3623", "mAge": "33.1", "mIncome": "50653"}, "2016": {"density": "2601.166", "totalPop": "4503", "mAge": "33.9", "mIncome": "49882"}, "2017": {"density": "2673.95", "totalPop": "4629", "mAge": "38.7", "mIncome": "49844"}, "2011": {"density": "2242.05", "totalPop": "3748", "mAge": "35.1", "mIncome": "51512"}, "2018": {"density": "2740.38", "totalPop": "4744", "mAge": "38", "mIncome": "52335"}, "2012": {"density": "2365.877", "totalPop": "3955", "mAge": "32.1", "mIncome": "51831"}, "2020": {"density": "2659.895", "totalPop": "5015", "mAge": "40.4", "mIncome": "55037"}, "2014": {"density": "2400.573", "totalPop": "4013", "mAge": "38.3", "mIncome": "50427"}, "2015": {"density": "2624.898", "totalPop": "4388", "mAge": "35.8", "mIncome": "50745"}, "2022": {"density": "2680.05", "totalPop": "5053", "mAge": "33.7", "mIncome": "69694"}, "2013": {"density": "2338.36", "totalPop": "3909", "mAge": "32.8", "mIncome": "52628"}, "2021": {"density": "2664.669", "totalPop": "5024", "mAge": "36.2", "mIncome": "61536"}, "2019": {"density": "2809.698", "totalPop": "4864", "mAge": "34.5", "mIncome": "51834"}, "name": "Census Tract 449, Wyandotte County, Kansas"}