{"2010": {"density": "24.24871", "totalPop": "7327", "mAge": "37.8", "mIncome": "47969"}, "2016": {"density": "24.29304", "totalPop": "7341", "mAge": "43.3", "mIncome": "57138"}, "2017": {"density": "22.88331", "totalPop": "6915", "mAge": "45.1", "mIncome": "57196"}, "2011": {"density": "23.97732", "totalPop": "7245", "mAge": "38.1", "mIncome": "47644"}, "2018": {"density": "22.01071", "totalPop": "6652", "mAge": "45.2", "mIncome": "50471"}, "2012": {"density": "24.67497", "totalPop": "7456", "mAge": "37.7", "mIncome": "51786"}, "2014": {"density": "24.18566", "totalPop": "7308", "mAge": "37.9", "mIncome": "58152"}, "2015": {"density": "24.47027", "totalPop": "7394", "mAge": "41", "mIncome": "55678"}, "2013": {"density": "24.90051", "totalPop": "7524", "mAge": "38", "mIncome": "57523"}, "2019": {"density": "22.0802", "totalPop": "6673", "mAge": "45.6", "mIncome": "57698"}, "name": "Census Tract 211, Lafourche Parish, Louisiana"}