{"2010": {"density": "5.464692", "totalPop": "638", "mAge": "39", "mIncome": "21167"}, "2016": {"density": "10.32595", "totalPop": "1206", "mAge": "39.6", "mIncome": "31023"}, "2017": {"density": "9.093003", "totalPop": "1062", "mAge": "44.8", "mIncome": "33421"}, "2011": {"density": "7.76875", "totalPop": "907", "mAge": "27.1", "mIncome": "22614"}, "2018": {"density": "8.20254", "totalPop": "958", "mAge": "43.5", "mIncome": "31354"}, "2012": {"density": "10.85216", "totalPop": "1267", "mAge": "26", "mIncome": "28125"}, "2020": {"density": "8.412391", "totalPop": "982", "mAge": "33.8", "mIncome": "34770"}, "2014": {"density": "10.34788", "totalPop": "1208", "mAge": "39.5", "mIncome": "28355"}, "2015": {"density": "10.53635", "totalPop": "1230", "mAge": "40", "mIncome": "31000"}, "2022": {"density": "7.572865", "totalPop": "884", "mAge": "33.5", "mIncome": "25547"}, "2013": {"density": "9.542487", "totalPop": "1114", "mAge": "39.4", "mIncome": "30083"}, "2021": {"density": "7.975494", "totalPop": "931", "mAge": "34.1", "mIncome": "37065"}, "2019": {"density": "7.84293", "totalPop": "916", "mAge": "38.6", "mIncome": "33981"}, "name": "Census Tract 508, Plaquemines Parish, Louisiana"}