{"2010": {"density": "7756.234", "totalPop": "3342", "mAge": "40.8", "mIncome": "30677"}, "2016": {"density": "8088.186", "totalPop": "3485", "mAge": "36.5", "mIncome": "40711"}, "2017": {"density": "7649.544", "totalPop": "3296", "mAge": "42.2", "mIncome": "41962"}, "2011": {"density": "7786.405", "totalPop": "3355", "mAge": "45.1", "mIncome": "31933"}, "2018": {"density": "7888.585", "totalPop": "3399", "mAge": "38.3", "mIncome": "35529"}, "2012": {"density": "8396.785", "totalPop": "3618", "mAge": "41.2", "mIncome": "33721"}, "2020": {"density": "7974.161", "totalPop": "3428", "mAge": "46.1", "mIncome": "24464"}, "2014": {"density": "8290.101", "totalPop": "3572", "mAge": "41.5", "mIncome": "41075"}, "2015": {"density": "8248.325", "totalPop": "3554", "mAge": "38.5", "mIncome": "36552"}, "2022": {"density": "8485.922", "totalPop": "3648", "mAge": "43.3", "mIncome": "27500"}, "2013": {"density": "8345.801", "totalPop": "3596", "mAge": "42.9", "mIncome": "35904"}, "2021": {"density": "8599.905", "totalPop": "3697", "mAge": "45", "mIncome": "24509"}, "2019": {"density": "7709.879", "totalPop": "3322", "mAge": "41.7", "mIncome": "27450"}, "name": "Census Tract 8, Washington County, Maryland"}