{"2010": {"density": "58.46627", "totalPop": "4221", "mAge": "38.6", "mIncome": "54250"}, "2016": {"density": "54.00614", "totalPop": "3899", "mAge": "39.5", "mIncome": "52879"}, "2017": {"density": "53.67371", "totalPop": "3875", "mAge": "39.1", "mIncome": "56058"}, "2011": {"density": "56.48553", "totalPop": "4078", "mAge": "38.3", "mIncome": "51108"}, "2018": {"density": "55.40456", "totalPop": "4000", "mAge": "38.6", "mIncome": "59077"}, "2012": {"density": "56.13924", "totalPop": "4053", "mAge": "39.3", "mIncome": "52955"}, "2020": {"density": "55.57077", "totalPop": "4012", "mAge": "40.9", "mIncome": "59472"}, "2014": {"density": "53.25817", "totalPop": "3845", "mAge": "42.2", "mIncome": "50101"}, "2015": {"density": "52.82878", "totalPop": "3814", "mAge": "42.5", "mIncome": "50274"}, "2022": {"density": "55.3353", "totalPop": "3995", "mAge": "41", "mIncome": "69261"}, "2013": {"density": "54.33857", "totalPop": "3923", "mAge": "40", "mIncome": "48233"}, "2021": {"density": "53.93633", "totalPop": "3894", "mAge": "40.7", "mIncome": "64786"}, "2019": {"density": "56.67886", "totalPop": "4092", "mAge": "40.1", "mIncome": "59375"}, "name": "Census Tract 207, Eaton County, Michigan"}