{"2010": {"density": "4710.152", "totalPop": "1202", "mAge": "47.4", "mIncome": "36706"}, "2016": {"density": "6751.75", "totalPop": "1723", "mAge": "37.4", "mIncome": "35165"}, "2017": {"density": "7002.541", "totalPop": "1787", "mAge": "35.5", "mIncome": "36964"}, "2011": {"density": "5924.917", "totalPop": "1512", "mAge": "39.6", "mIncome": "36745"}, "2018": {"density": "6226.658", "totalPop": "1589", "mAge": "39.2", "mIncome": "38380"}, "2012": {"density": "5924.917", "totalPop": "1512", "mAge": "41", "mIncome": "33594"}, "2020": {"density": "8142.94", "totalPop": "2078", "mAge": "33.1", "mIncome": "36609"}, "2014": {"density": "6775.262", "totalPop": "1729", "mAge": "37", "mIncome": "37200"}, "2015": {"density": "6736.076", "totalPop": "1719", "mAge": "35.8", "mIncome": "42719"}, "2022": {"density": "8193.883", "totalPop": "2091", "mAge": "33.4", "mIncome": "44648"}, "2013": {"density": "6387.321", "totalPop": "1630", "mAge": "38.6", "mIncome": "33947"}, "2021": {"density": "8354.547", "totalPop": "2132", "mAge": "33.3", "mIncome": "49167"}, "2019": {"density": "6493.123", "totalPop": "1657", "mAge": "38.8", "mIncome": "44044"}, "name": "Census Tract 5388, Wayne County, Michigan"}