{"2010": {"density": "5258.301", "totalPop": "6283", "mAge": "42.7", "mIncome": "47147"}, "2016": {"density": "5454.974", "totalPop": "6518", "mAge": "38.9", "mIncome": "51222"}, "2017": {"density": "5523.601", "totalPop": "6600", "mAge": "37.2", "mIncome": "52582"}, "2011": {"density": "5242.396", "totalPop": "6264", "mAge": "43.3", "mIncome": "47958"}, "2018": {"density": "5401.417", "totalPop": "6454", "mAge": "38.6", "mIncome": "55262"}, "2012": {"density": "5223.987", "totalPop": "6242", "mAge": "42.6", "mIncome": "44967"}, "2020": {"density": "5096.784", "totalPop": "6090", "mAge": "40.5", "mIncome": "49457"}, "2014": {"density": "5461.669", "totalPop": "6526", "mAge": "41.3", "mIncome": "46931"}, "2015": {"density": "5610.64", "totalPop": "6704", "mAge": "38.9", "mIncome": "46735"}, "2022": {"density": "5075.861", "totalPop": "6065", "mAge": "41", "mIncome": "54478"}, "2013": {"density": "5211.434", "totalPop": "6227", "mAge": "42.7", "mIncome": "45950"}, "2021": {"density": "5223.994", "totalPop": "6242", "mAge": "39.4", "mIncome": "50124"}, "2019": {"density": "5398.907", "totalPop": "6451", "mAge": "38.5", "mIncome": "54960"}, "name": "Census Tract 2205.01, St. Louis County, Missouri"}