{"2010": {"density": "24323.32", "totalPop": "3957", "mAge": "37.2", "mIncome": "43990"}, "2016": {"density": "23388.68", "totalPop": "3800", "mAge": "38.4", "mIncome": "38491"}, "2017": {"density": "24287.29", "totalPop": "3946", "mAge": "39.3", "mIncome": "44542"}, "2011": {"density": "22854.21", "totalPop": "3718", "mAge": "39.2", "mIncome": "46932"}, "2018": {"density": "22003.87", "totalPop": "3575", "mAge": "38.8", "mIncome": "45819"}, "2012": {"density": "23155.41", "totalPop": "3767", "mAge": "37.5", "mIncome": "45101"}, "2020": {"density": "22213.14", "totalPop": "3609", "mAge": "37.4", "mIncome": "51797"}, "2014": {"density": "22277.31", "totalPop": "3617", "mAge": "39.6", "mIncome": "44137"}, "2015": {"density": "22794.67", "totalPop": "3701", "mAge": "39.5", "mIncome": "39766"}, "2022": {"density": "21259.13", "totalPop": "3454", "mAge": "38.6", "mIncome": "70909"}, "2013": {"density": "23475.05", "totalPop": "3819", "mAge": "37.1", "mIncome": "43523"}, "2021": {"density": "23185.62", "totalPop": "3767", "mAge": "40.8", "mIncome": "53718"}, "2019": {"density": "24176.56", "totalPop": "3928", "mAge": "38.3", "mIncome": "63788"}, "name": "Census Tract 125, Essex County, New Jersey"}