{"2010": {"density": "1535.433", "totalPop": "2972", "mAge": "37", "mIncome": "118500"}, "2016": {"density": "1638.243", "totalPop": "3171", "mAge": "39.8", "mIncome": "147171"}, "2017": {"density": "1579.863", "totalPop": "3058", "mAge": "41", "mIncome": "148073"}, "2011": {"density": "1500.818", "totalPop": "2905", "mAge": "38.5", "mIncome": "126964"}, "2018": {"density": "1512.185", "totalPop": "2927", "mAge": "42.4", "mIncome": "147708"}, "2012": {"density": "1549.899", "totalPop": "3000", "mAge": "38.7", "mIncome": "125781"}, "2020": {"density": "1566.041", "totalPop": "3031", "mAge": "42.8", "mIncome": "167222"}, "2014": {"density": "1653.226", "totalPop": "3200", "mAge": "38.5", "mIncome": "133281"}, "2015": {"density": "1655.808", "totalPop": "3205", "mAge": "39.3", "mIncome": "134737"}, "2022": {"density": "1549.508", "totalPop": "2999", "mAge": "43", "mIncome": "186250"}, "2013": {"density": "1636.693", "totalPop": "3168", "mAge": "38.5", "mIncome": "135982"}, "2021": {"density": "1657.493", "totalPop": "3208", "mAge": "42.5", "mIncome": "175144"}, "2019": {"density": "1470.337", "totalPop": "2846", "mAge": "44", "mIncome": "156450"}, "name": "Census Tract 537.04, Somerset County, New Jersey"}