{"2010": {"density": "98048.15", "totalPop": "2857", "mAge": "34.6", "mIncome": "51536"}, "2016": {"density": "143005.5", "totalPop": "4167", "mAge": "35.2", "mIncome": "55903"}, "2017": {"density": "124748", "totalPop": "3635", "mAge": "36.3", "mIncome": "57161"}, "2011": {"density": "115173.1", "totalPop": "3356", "mAge": "32.5", "mIncome": "52774"}, "2018": {"density": "129484", "totalPop": "3773", "mAge": "38.6", "mIncome": "73640"}, "2012": {"density": "131749", "totalPop": "3839", "mAge": "31.5", "mIncome": "52679"}, "2020": {"density": "124994.9", "totalPop": "3642", "mAge": "40.2", "mIncome": "73723"}, "2014": {"density": "151276.3", "totalPop": "4408", "mAge": "30.9", "mIncome": "57150"}, "2015": {"density": "142593.7", "totalPop": "4155", "mAge": "34.1", "mIncome": "54913"}, "2022": {"density": "160550.8", "totalPop": "4678", "mAge": "36.4", "mIncome": "76047"}, "2013": {"density": "134151.3", "totalPop": "3909", "mAge": "30.7", "mIncome": "53992"}, "2021": {"density": "138414.1", "totalPop": "4033", "mAge": "40.1", "mIncome": "71436"}, "2019": {"density": "128042.6", "totalPop": "3731", "mAge": "39.2", "mIncome": "63807"}, "name": "Census Tract 259, New York County, New York"}