{"2010": {"density": "855.4485", "totalPop": "2488", "mAge": "39.5", "mIncome": "74200"}, "2016": {"density": "796.0436", "totalPop": "2329", "mAge": "42.3", "mIncome": "96597"}, "2017": {"density": "820.2606", "totalPop": "2400", "mAge": "43.6", "mIncome": "98750"}, "2011": {"density": "843.0702", "totalPop": "2452", "mAge": "38.9", "mIncome": "79354"}, "2018": {"density": "885.5397", "totalPop": "2591", "mAge": "40.5", "mIncome": "90385"}, "2012": {"density": "856.1991", "totalPop": "2505", "mAge": "38.4", "mIncome": "90056"}, "2020": {"density": "836.5772", "totalPop": "2448", "mAge": "36.7", "mIncome": "108148"}, "2014": {"density": "769.7253", "totalPop": "2252", "mAge": "43.1", "mIncome": "99250"}, "2015": {"density": "784.7643", "totalPop": "2296", "mAge": "43.7", "mIncome": "94808"}, "2022": {"density": "884.7624", "totalPop": "2589", "mAge": "38.5", "mIncome": "118672"}, "2013": {"density": "793.3093", "totalPop": "2321", "mAge": "43.1", "mIncome": "98292"}, "2021": {"density": "864.9415", "totalPop": "2531", "mAge": "42.3", "mIncome": "99250"}, "2019": {"density": "882.8055", "totalPop": "2583", "mAge": "39.6", "mIncome": "92788"}, "name": "Census Tract 330.02, Schenectady County, New York"}