{"2010": {"density": "1843.935", "totalPop": "6920", "mAge": "32.1", "mIncome": "34311"}, "2016": {"density": "2316.425", "totalPop": "8695", "mAge": "31.3", "mIncome": "53443"}, "2017": {"density": "2306.302", "totalPop": "8657", "mAge": "31.4", "mIncome": "57426"}, "2011": {"density": "1782.115", "totalPop": "6688", "mAge": "32.1", "mIncome": "37434"}, "2018": {"density": "2178.425", "totalPop": "8177", "mAge": "30.7", "mIncome": "56917"}, "2012": {"density": "1779.985", "totalPop": "6680", "mAge": "32.3", "mIncome": "38250"}, "2014": {"density": "2113.421", "totalPop": "7933", "mAge": "30.4", "mIncome": "50024"}, "2015": {"density": "2209.595", "totalPop": "8294", "mAge": "30", "mIncome": "52940"}, "2013": {"density": "1935.193", "totalPop": "7264", "mAge": "30", "mIncome": "41415"}, "2019": {"density": "2084.116", "totalPop": "7823", "mAge": "29.7", "mIncome": "52117"}, "name": "Census Tract 107, Ward County, North Dakota"}