{"2010": {"density": "6423.607", "totalPop": "1850", "mAge": "15.6", "mIncome": "6941"}, "2016": {"density": "7489.177", "totalPop": "2157", "mAge": "20.7", "mIncome": "7945"}, "2017": {"density": "7714.859", "totalPop": "2222", "mAge": "20.1", "mIncome": "8733"}, "2011": {"density": "6666.663", "totalPop": "1920", "mAge": "16.8", "mIncome": "7748"}, "2018": {"density": "7697.479", "totalPop": "2217", "mAge": "21.3", "mIncome": "8946"}, "2012": {"density": "6308.677", "totalPop": "1817", "mAge": "16", "mIncome": "6146"}, "2020": {"density": "8520.349", "totalPop": "2454", "mAge": "18.9", "mIncome": "10789"}, "2014": {"density": "6183.692", "totalPop": "1781", "mAge": "20.2", "mIncome": "6522"}, "2015": {"density": "6961.428", "totalPop": "2005", "mAge": "22.1", "mIncome": "7215"}, "2022": {"density": "7305.14", "totalPop": "2104", "mAge": "28.2", "mIncome": "14161"}, "2013": {"density": "6971.844", "totalPop": "2008", "mAge": "18", "mIncome": "6949"}, "2021": {"density": "7496.101", "totalPop": "2159", "mAge": "22.6", "mIncome": "11793"}, "2019": {"density": "8062.041", "totalPop": "2322", "mAge": "21.1", "mIncome": "9413"}, "name": "Census Tract 1098.01, Cuyahoga County, Ohio"}