{"2010": {"density": "2441.743", "totalPop": "5117", "mAge": "19.2", "mIncome": "11474"}, "2016": {"density": "2476.577", "totalPop": "5190", "mAge": "18.5", "mIncome": "10245"}, "2017": {"density": "2483.257", "totalPop": "5204", "mAge": "21.7", "mIncome": "11600"}, "2011": {"density": "2250.869", "totalPop": "4717", "mAge": "20.6", "mIncome": "13608"}, "2018": {"density": "2591.577", "totalPop": "5431", "mAge": "22.6", "mIncome": "12092"}, "2012": {"density": "2295.247", "totalPop": "4810", "mAge": "20.1", "mIncome": "12202"}, "2020": {"density": "2995.696", "totalPop": "6204", "mAge": "22.3", "mIncome": "17949"}, "2014": {"density": "2338.671", "totalPop": "4901", "mAge": "21.4", "mIncome": "9681"}, "2015": {"density": "2294.77", "totalPop": "4809", "mAge": "20.7", "mIncome": "9531"}, "2022": {"density": "3237.857", "totalPop": "6741", "mAge": "23", "mIncome": "19018"}, "2013": {"density": "2488.983", "totalPop": "5216", "mAge": "20.1", "mIncome": "9851"}, "2021": {"density": "3023.152", "totalPop": "6294", "mAge": "22.1", "mIncome": "17377"}, "2019": {"density": "2901.054", "totalPop": "6008", "mAge": "17.9", "mIncome": "14731"}, "name": "Census Tract 80, Hamilton County, Ohio"}