{"2010": {"density": "32.16996", "totalPop": "4803", "mAge": "49.9", "mIncome": "31977"}, "2016": {"density": "35.38496", "totalPop": "5283", "mAge": "47", "mIncome": "27071"}, "2017": {"density": "34.03199", "totalPop": "5081", "mAge": "49.2", "mIncome": "30422"}, "2011": {"density": "31.68771", "totalPop": "4731", "mAge": "49.2", "mIncome": "25855"}, "2018": {"density": "34.60801", "totalPop": "5167", "mAge": "48", "mIncome": "30938"}, "2012": {"density": "32.71249", "totalPop": "4884", "mAge": "49", "mIncome": "26438"}, "2020": {"density": "34.21948", "totalPop": "5109", "mAge": "49.1", "mIncome": "31340"}, "2014": {"density": "32.82635", "totalPop": "4901", "mAge": "48", "mIncome": "26809"}, "2015": {"density": "34.34008", "totalPop": "5127", "mAge": "47.6", "mIncome": "26070"}, "2022": {"density": "34.12736", "totalPop": "5095", "mAge": "48.9", "mIncome": "37191"}, "2013": {"density": "32.46467", "totalPop": "4847", "mAge": "47.5", "mIncome": "25885"}, "2021": {"density": "33.37555", "totalPop": "4983", "mAge": "49.1", "mIncome": "34150"}, "2019": {"density": "34.23288", "totalPop": "5111", "mAge": "47.6", "mIncome": "31856"}, "name": "Census Tract 9550, Clay County, Tennessee"}