{"2010": {"density": "383.126", "totalPop": "2032", "mAge": "29.8", "mIncome": "41500"}, "2016": {"density": "365.9682", "totalPop": "1941", "mAge": "34.1", "mIncome": "37011"}, "2017": {"density": "381.0519", "totalPop": "2021", "mAge": "32.5", "mIncome": "43269"}, "2011": {"density": "379.9207", "totalPop": "2015", "mAge": "33.4", "mIncome": "44583"}, "2018": {"density": "375.207", "totalPop": "1990", "mAge": "32.3", "mIncome": "41705"}, "2012": {"density": "355.4097", "totalPop": "1885", "mAge": "34.1", "mIncome": "37011"}, "2020": {"density": "358.632", "totalPop": "1879", "mAge": "35", "mIncome": "46654"}, "2014": {"density": "390.6678", "totalPop": "2072", "mAge": "33.5", "mIncome": "35000"}, "2015": {"density": "385.5771", "totalPop": "2045", "mAge": "34.2", "mIncome": "34716"}, "2022": {"density": "341.2635", "totalPop": "1788", "mAge": "35.5", "mIncome": "49107"}, "2013": {"density": "374.8299", "totalPop": "1988", "mAge": "35.2", "mIncome": "37105"}, "2021": {"density": "349.8524", "totalPop": "1833", "mAge": "29.7", "mIncome": "44792"}, "2019": {"density": "348.999", "totalPop": "1851", "mAge": "36.7", "mIncome": "41250"}, "name": "Census Tract 9502, Donley County, Texas"}