{"2010": {"density": "3278.789", "totalPop": "6416", "mAge": "23.8", "mIncome": "24119"}, "2016": {"density": "3506.538", "totalPop": "6868", "mAge": "26.4", "mIncome": "26442"}, "2017": {"density": "3596.907", "totalPop": "7045", "mAge": "28.4", "mIncome": "28294"}, "2011": {"density": "3570.077", "totalPop": "6986", "mAge": "25.8", "mIncome": "25417"}, "2018": {"density": "3553.509", "totalPop": "6960", "mAge": "30", "mIncome": "31859"}, "2012": {"density": "3585.408", "totalPop": "7016", "mAge": "25.1", "mIncome": "25290"}, "2014": {"density": "4000.838", "totalPop": "7829", "mAge": "22.8", "mIncome": "25165"}, "2015": {"density": "3651.537", "totalPop": "7152", "mAge": "24.7", "mIncome": "24462"}, "2013": {"density": "3760.656", "totalPop": "7359", "mAge": "24.7", "mIncome": "26308"}, "2019": {"density": "3417.7", "totalPop": "6694", "mAge": "28.7", "mIncome": "36393"}, "name": "Census Tract 104.07, El Paso County, Texas"}