{"2010": {"density": "36.28748", "totalPop": "4150", "mAge": "32.5", "mIncome": "71442"}, "2016": {"density": "33.24458", "totalPop": "3802", "mAge": "40.1", "mIncome": "42371"}, "2017": {"density": "31.09356", "totalPop": "3556", "mAge": "40.3", "mIncome": "41708"}, "2011": {"density": "32.90357", "totalPop": "3763", "mAge": "37.4", "mIncome": "65750"}, "2018": {"density": "28.9338", "totalPop": "3309", "mAge": "43.5", "mIncome": "39875"}, "2012": {"density": "35.78907", "totalPop": "4093", "mAge": "37.9", "mIncome": "52036"}, "2020": {"density": "23.21525", "totalPop": "2655", "mAge": "46.7", "mIncome": "50700"}, "2014": {"density": "35.6142", "totalPop": "4073", "mAge": "40.7", "mIncome": "48908"}, "2015": {"density": "35.68415", "totalPop": "4081", "mAge": "42.8", "mIncome": "45463"}, "2022": {"density": "19.01814", "totalPop": "2175", "mAge": "50.2", "mIncome": "49141"}, "2013": {"density": "34.1627", "totalPop": "3907", "mAge": "39.5", "mIncome": "49383"}, "2021": {"density": "20.25978", "totalPop": "2317", "mAge": "50", "mIncome": "37097"}, "2019": {"density": "27.49979", "totalPop": "3145", "mAge": "44.3", "mIncome": "44781"}, "name": "Census Tract 9504, Newton County, Texas"}