{"2010": {"density": "156.8714", "totalPop": "3505", "mAge": "38.3", "mIncome": "66902"}, "2016": {"density": "181.1364", "totalPop": "4047", "mAge": "41.6", "mIncome": "66919"}, "2017": {"density": "169.6335", "totalPop": "3790", "mAge": "43.3", "mIncome": "69814"}, "2011": {"density": "163.0477", "totalPop": "3643", "mAge": "41.7", "mIncome": "75143"}, "2018": {"density": "171.1553", "totalPop": "3824", "mAge": "41.1", "mIncome": "72500"}, "2012": {"density": "175.5339", "totalPop": "3922", "mAge": "39.6", "mIncome": "72700"}, "2020": {"density": "177.2872", "totalPop": "3961", "mAge": "37.1", "mIncome": "82424"}, "2014": {"density": "169.5439", "totalPop": "3788", "mAge": "42.9", "mIncome": "66960"}, "2015": {"density": "179.5698", "totalPop": "4012", "mAge": "43.1", "mIncome": "60931"}, "2022": {"density": "187.5369", "totalPop": "4190", "mAge": "36.8", "mIncome": "84896"}, "2013": {"density": "181.6655", "totalPop": "4059", "mAge": "42.2", "mIncome": "75443"}, "2021": {"density": "177.9586", "totalPop": "3976", "mAge": "36.6", "mIncome": "83810"}, "2019": {"density": "172.8114", "totalPop": "3861", "mAge": "40.3", "mIncome": "80526"}, "name": "Census Tract 214, Orange County, Texas"}