{"2010": {"density": "4506.772", "totalPop": "3347", "mAge": "27.2", "mIncome": "36897"}, "2016": {"density": "4771.188", "totalPop": "3572", "mAge": "33.7", "mIncome": "34392"}, "2017": {"density": "4708.409", "totalPop": "3525", "mAge": "33.1", "mIncome": "34952"}, "2011": {"density": "4268.437", "totalPop": "3170", "mAge": "29", "mIncome": "35515"}, "2018": {"density": "4665.666", "totalPop": "3493", "mAge": "33.6", "mIncome": "33523"}, "2012": {"density": "4668.351", "totalPop": "3467", "mAge": "30.7", "mIncome": "35345"}, "2014": {"density": "4540.43", "totalPop": "3372", "mAge": "33.8", "mIncome": "34767"}, "2015": {"density": "4606.409", "totalPop": "3421", "mAge": "34.3", "mIncome": "35345"}, "2013": {"density": "4727.595", "totalPop": "3511", "mAge": "33.6", "mIncome": "33567"}, "2019": {"density": "4477.329", "totalPop": "3352", "mAge": "39.6", "mIncome": "36493"}, "name": "Census Tract 653, Suffolk city, Virginia"}