{"2010": {"density": "400.2393", "totalPop": "1804", "mAge": "48", "mIncome": "13594"}, "2016": {"density": "318.1228", "totalPop": "1434", "mAge": "51", "mIncome": "19712"}, "2017": {"density": "331.6552", "totalPop": "1495", "mAge": "49.5", "mIncome": "18871"}, "2011": {"density": "404.0109", "totalPop": "1821", "mAge": "48.1", "mIncome": "14363"}, "2018": {"density": "334.761", "totalPop": "1509", "mAge": "50.2", "mIncome": "21852"}, "2012": {"density": "372.0518", "totalPop": "1677", "mAge": "46", "mIncome": "16328"}, "2020": {"density": "338.0886", "totalPop": "1524", "mAge": "54.7", "mIncome": "25950"}, "2014": {"density": "357.4094", "totalPop": "1611", "mAge": "45.7", "mIncome": "22171"}, "2015": {"density": "345.651", "totalPop": "1558", "mAge": "48.7", "mIncome": "20938"}, "2022": {"density": "", "totalPop": "1551", "mAge": "52.5", "mIncome": "45486"}, "2013": {"density": "366.9492", "totalPop": "1654", "mAge": "44.7", "mIncome": "17983"}, "2021": {"density": "361.6039", "totalPop": "1630", "mAge": "47.8", "mIncome": "41893"}, "2019": {"density": "305.034", "totalPop": "1375", "mAge": "56.1", "mIncome": "21875"}, "name": "Census Tract 19, Mercer County, West Virginia"}