{"2010": {"density": "41543.32", "totalPop": "3352", "mAge": "36.8", "mIncome": "14533"}, "2016": {"density": "29352.94", "totalPop": "2368", "mAge": "46.9", "mIncome": "17613"}, "2017": {"density": "28448.06", "totalPop": "2295", "mAge": "45.5", "mIncome": "16298"}, "2011": {"density": "40291.38", "totalPop": "3251", "mAge": "40.3", "mIncome": "14762"}, "2018": {"density": "24345.09", "totalPop": "1964", "mAge": "48.2", "mIncome": "14214"}, "2012": {"density": "35953.64", "totalPop": "2901", "mAge": "42.1", "mIncome": "15895"}, "2020": {"density": "20675.68", "totalPop": "1668", "mAge": "49.6", "mIncome": "14900"}, "2014": {"density": "34088.09", "totalPop": "2750", "mAge": "45.3", "mIncome": "17945"}, "2015": {"density": "33331.95", "totalPop": "2689", "mAge": "45.8", "mIncome": "17802"}, "2022": {"density": "", "totalPop": "1845", "mAge": "52.7", "mIncome": "10948"}, "2013": {"density": "35742.95", "totalPop": "2884", "mAge": "40.5", "mIncome": "17589"}, "2021": {"density": "25423.15", "totalPop": "2051", "mAge": "46.5", "mIncome": "13761"}, "2019": {"density": "21171.5", "totalPop": "1708", "mAge": "50.6", "mIncome": "13585"}, "name": "Census Tract 31, San Juan Municipio, Puerto Rico"}